one bIt adder/adder.sv
module rtl_adder
    (input  logic a, b, ci,
     output logic sum, co
    );

    assign {co, sum} = a + b + ci;

endmodule: rtl_adder

one bIt adder/tb_adder.sv
module tb_adder;
    logic   a, b, ci;
    logic   sum, co;

    rtl_adder dut (
        .a(a),  .b(b),  .ci(ci),
        .sum(sum),  .co(co)
    );

    initial begin
        $dumpfile("adder.vcd");
        $dumpvars(0, tb_adder);

        //Test all 8 input combinations
        {a, b, ci} = 3'b000; #10;
        {a, b, ci} = 3'b001; #10;
        {a, b, ci} = 3'b010; #10;
        {a, b, ci} = 3'b011; #10;
        {a, b, ci} = 3'b100; #10;
        {a, b, ci} = 3'b101; #10;
        {a, b, ci} = 3'b110; #10;
        {a, b, ci} = 3'b111; #10;
        
        $display("All test complete.");
        $finish;
    end

    //Print result
    initial begin
        $monitor("a = %b b = %b ci = %b | sum = %b co = %b", a, b, ci, sum, co);
    end
endmodule

one bIt adder/adder.vcd
$date
	Fri Feb 13 23:59:22 2026
$end
$version
	Icarus Verilog
$end
$timescale
	1s
$end
$scope module tb_adder $end
$var wire 1 ! sum $end
$var wire 1 " co $end
$var reg 1 # a $end
$var reg 1 $ b $end
$var reg 1 % ci $end
$scope module dut $end
$var wire 1 # a $end
$var wire 1 $ b $end
$var wire 1 % ci $end
$var wire 1 ! sum $end
$var wire 1 " co $end
$upscope $end
$upscope $end
$enddefinitions $end
#0
$dumpvars
0%
0$
0#
0"
0!
$end
#10
1!
1%
#20
1$
0%
#30
0!
1"
1%
#40
1!
0"
1#
0$
0%
#50
0!
1"
1%
#60
1$
0%
#70
1!
1%
